restnavigator-1.0.1.dist-info/DESCRIPTION.rst
restnavigator-1.0.1.dist-info/METADATA
restnavigator-1.0.1.dist-info/top_level.txt
restnavigator-1.0.1.dist-info/WHEEL
restnavigator-1.0.1.dist-info/metadata.json
restnavigator-1.0.1.dist-info/RECORD
restnavigator/utils.py
restnavigator/registry.py
restnavigator/exc.py
restnavigator/__init__.py
restnavigator/halnav.py
